<?xml version="1.0" encoding="utf-8"?>
<odoo>
    <data noupdate="1">
        <record id="en_apply_in_personal_income" model="ir.config_parameter">
            <field name="key">en.apply.in.personal.income</field>
            <field name="value">1</field>
        </record>
        <record id="en_apply_in_personal_exit" model="ir.config_parameter">
            <field name="key">en.apply.in.personal.exit</field>
            <field name="value">1</field>
        </record>
        <record id="en_apply_in_birthday" model="ir.config_parameter">
            <field name="key">en.apply.in.birthday</field>
            <field name="value">1</field>
        </record>
        <record id="en_apply_in_anniversary" model="ir.config_parameter">
            <field name="key">en.apply.in.anniversary</field>
            <field name="value">1</field>
        </record>
        <record id="en_apply_in_profession_celebration_date" model="ir.config_parameter">
            <field name="key">en.apply.in.profession.celebration.date</field>
            <field name="value">1</field>
        </record>
        <record id="en_notify_administrators" model="ir.config_parameter">
            <field name="key">en.notify.administrators</field>
            <field name="value">1</field>
        </record>
        <record id="en_anticipation_days" model="ir.config_parameter">
            <field name="key">en.anticipation.days</field>
            <field name="value">5</field>
        </record>
        <record id="en_email_for_mass_notifications" model="ir.config_parameter">
            <field name="key">en.email.for.mass.notifications</field>
            <field name="value"/>
        </record>
    </data>
</odoo>